pygments-stubs/METADATA.toml
pygments-stubs/__init__.pyi
pygments-stubs/cmdline.pyi
pygments-stubs/console.pyi
pygments-stubs/filter.pyi
pygments-stubs/formatter.pyi
pygments-stubs/lexer.pyi
pygments-stubs/modeline.pyi
pygments-stubs/plugin.pyi
pygments-stubs/py.typed
pygments-stubs/regexopt.pyi
pygments-stubs/scanner.pyi
pygments-stubs/sphinxext.pyi
pygments-stubs/style.pyi
pygments-stubs/token.pyi
pygments-stubs/unistring.pyi
pygments-stubs/util.pyi
pygments-stubs/filters/__init__.pyi
pygments-stubs/formatters/__init__.pyi
pygments-stubs/formatters/_mapping.pyi
pygments-stubs/formatters/bbcode.pyi
pygments-stubs/formatters/html.pyi
pygments-stubs/formatters/img.pyi
pygments-stubs/formatters/irc.pyi
pygments-stubs/formatters/latex.pyi
pygments-stubs/formatters/other.pyi
pygments-stubs/formatters/pangomarkup.pyi
pygments-stubs/formatters/rtf.pyi
pygments-stubs/formatters/svg.pyi
pygments-stubs/formatters/terminal.pyi
pygments-stubs/formatters/terminal256.pyi
pygments-stubs/lexers/__init__.pyi
pygments-stubs/lexers/javascript.pyi
pygments-stubs/lexers/jsx.pyi
pygments-stubs/lexers/kusto.pyi
pygments-stubs/lexers/ldap.pyi
pygments-stubs/lexers/lean.pyi
pygments-stubs/lexers/lisp.pyi
pygments-stubs/lexers/prql.pyi
pygments-stubs/lexers/vip.pyi
pygments-stubs/lexers/vyper.pyi
pygments-stubs/styles/__init__.pyi
types_pygments-2.19.0.20250715.dist-info/licenses/LICENSE
types_pygments-2.19.0.20250715.dist-info/METADATA
types_pygments-2.19.0.20250715.dist-info/WHEEL
types_pygments-2.19.0.20250715.dist-info/top_level.txt
types_pygments-2.19.0.20250715.dist-info/RECORD
